benchmark/backend_request_func.py
benchmark/benchmark_serving.py
benchmark/benchmark_serving_throughput.sh
benchmark/feishu.py
benchmark/report_to_feishu.py
configs/bp-sglang_openai_debug.yaml
configs/bp-sglang_openai_generation.yaml
configs/bp-sglang_openai_sleep.yaml
configs/bp-vllm-wp-2_openai_generation.yaml
configs/bp-vllm-wp_openai_generation.yaml
configs/bp-vllm_openai_generation.yaml
configs/install.sh
configs/nla-sglang_openai_generation.yaml
configs/nla-sglang_openai_multinode.yaml
configs/north-llm-api_service.yaml
configs/sglang_openai_generation.yaml
configs/sglang_openai_minilb.yaml
configs/sglang_openai_multinode.yaml
configs/sglang_openai_multinodeserving.yaml
configs/sglang_openai_pddec.yaml
configs/sglang_openai_pdpre.yaml
configs/sglang_openai_sleep.yaml
configs/sglang_router.yaml
configs/sglang_weaver_generation.yaml
configs/vllm-native_openai_generation.yaml
configs/vllm_anthropic_generation.yaml
configs/vllm_anthropic_multinode.yaml
configs/vllm_openai_generation.yaml
configs/vllm_openai_multinode.yaml
northserve/__init__.py
northserve/__main__.py
northserve/cli.py
northserve/constants.py
northserve/clients/__init__.py
northserve/clients/infrawave.py
northserve/clients/kubernetes.py
northserve/commands/__init__.py
northserve/commands/benchmark.py
northserve/commands/launch.py
northserve/commands/list.py
northserve/commands/north_llm_api.py
northserve/commands/stop.py
northserve/core/__init__.py
northserve/core/benchmark_engine.py
northserve/core/config_builder.py
northserve/core/job_manager.py
northserve/core/template_renderer.py
northserve/models/__init__.py
northserve/models/deployment.py
northserve/models/enums.py
northserve/utils/__init__.py
northserve/utils/helpers.py
northserve/utils/logger.py
northserve/utils/updater.py
northserve/utils/validator.py
yaml_templates/deployment.yaml.jinja
yaml_templates/deployment_multi_node.jinja
yaml_templates/deployment_pd_decode.jinja
yaml_templates/deployment_pd_minilb.jinja
northserve-2.0.6.dist-info/METADATA
northserve-2.0.6.dist-info/WHEEL
northserve-2.0.6.dist-info/entry_points.txt
northserve-2.0.6.dist-info/top_level.txt
northserve-2.0.6.dist-info/RECORD
