Metadata-Version: 2.4
Name: northserve
Version: 2.0.6
Summary: A one-click LLM serving deployment tool for Kubernetes
Home-page: https://github.com/china-qijizhifeng/NorthServing
Author: NorthServing Team
License: MIT
Project-URL: Homepage, https://github.com/china-qijizhifeng/NorthServing
Project-URL: Documentation, https://github.com/china-qijizhifeng/NorthServing#readme
Project-URL: Repository, https://github.com/china-qijizhifeng/NorthServing
Project-URL: Issues, https://github.com/china-qijizhifeng/NorthServing/issues
Keywords: llm,serving,kubernetes,volcano,deployment
Classifier: Development Status :: 4 - Beta
Classifier: Intended Audience :: Developers
Classifier: Topic :: Software Development :: Libraries :: Python Modules
Classifier: Programming Language :: Python :: 3
Classifier: Programming Language :: Python :: 3.8
Classifier: Programming Language :: Python :: 3.9
Classifier: Programming Language :: Python :: 3.10
Classifier: Programming Language :: Python :: 3.11
Requires-Python: >=3.8
Requires-Dist: click>=8.1.0
Requires-Dist: jinja2>=3.1.0
Requires-Dist: pyyaml>=6.0
Requires-Dist: requests>=2.31.0
Requires-Dist: colorama>=0.4.6
Requires-Dist: packaging>=23.0
Provides-Extra: dev
Requires-Dist: pytest>=7.4.0; extra == "dev"
Requires-Dist: pytest-mock>=3.11.0; extra == "dev"
Requires-Dist: pytest-cov>=4.1.0; extra == "dev"
Requires-Dist: black>=23.0.0; extra == "dev"
Requires-Dist: flake8>=6.0.0; extra == "dev"
Requires-Dist: mypy>=1.5.0; extra == "dev"
Requires-Dist: isort>=5.12.0; extra == "dev"
Requires-Dist: types-PyYAML>=6.0.0; extra == "dev"
Requires-Dist: types-requests>=2.31.0; extra == "dev"
Dynamic: home-page
Dynamic: requires-python
